AUTHORS.txt
CHANGES.rst
LICENSE.txt
MANIFEST.in
README.rst
setup.py
autofixture/__init__.py
autofixture/autofixtures.py
autofixture/base.py
autofixture/compat.py
autofixture/constraints.py
autofixture/generators.py
autofixture/models.py
autofixture/placeholder.py
autofixture/signals.py
autofixture/values.py
autofixture/management/__init__.py
autofixture/management/commands/__init__.py
autofixture/management/commands/loadtestdata.py
django_autofixture.egg-info/PKG-INFO
django_autofixture.egg-info/SOURCES.txt
django_autofixture.egg-info/dependency_links.txt
django_autofixture.egg-info/pbr.json
django_autofixture.egg-info/requires.txt
django_autofixture.egg-info/top_level.txt